{
  "id": "beth_horon_lower",
  "nombre": "Beth-horon Lower",
  "tipo": "ciudad",
  "nivel": 3,
  "lat": 31.8789,
  "lng": 35.1236,
  "frecuencia_at": 12,
  "jerarquia_pin": "menor",
  "descripcion_geo": "// PENDIENTE — Town in Ephraim and Dan, site of a famous battle.",
  "periodos_at": [
    "// PENDIENTE — verificar ocupación arqueológica"
  ],
  "historias": [
    {
      "id": "// PENDIENTE",
      "titulo": "// PENDIENTE",
      "fecha": "// PENDIENTE",
      "descripcion": "// PENDIENTE",
      "referencias": [
        "// PENDIENTE"
      ],
      "personajes_clave": [
        "// PENDIENTE"
      ]
    }
  ],
  "personajes": [
    {
      "id": "// PENDIENTE",
      "nombre": "// PENDIENTE",
      "emoji": "// PENDIENTE",
      "rol": "// PENDIENTE",
      "periodo": "// PENDIENTE",
      "descripcion": "// PENDIENTE",
      "referencias": [
        "// PENDIENTE"
      ],
      "ruta": []
    }
  ],
  "contexto_religioso": {
    "contexto_lugar": "// PENDIENTE",
    "religiones_presentes": [
      "// PENDIENTE"
    ]
  }
}